mysql/__init__.py
mysql_client-0.0.1.dist-info/LICENSE
mysql_client-0.0.1.dist-info/METADATA
mysql_client-0.0.1.dist-info/WHEEL
mysql_client-0.0.1.dist-info/top_level.txt
mysql_client-0.0.1.dist-info/RECORD
